git_llm_tool/__init__.py
git_llm_tool/__main__.py
git_llm_tool/cli.py
git_llm_tool/commands/__init__.py
git_llm_tool/commands/changelog_cmd.py
git_llm_tool/commands/commit_cmd.py
git_llm_tool/core/__init__.py
git_llm_tool/core/config.py
git_llm_tool/core/diff_optimizer.py
git_llm_tool/core/exceptions.py
git_llm_tool/core/git_helper.py
git_llm_tool/core/jira_helper.py
git_llm_tool/core/rate_limiter.py
git_llm_tool/core/smart_chunker.py
git_llm_tool/core/token_counter.py
git_llm_tool/providers/__init__.py
git_llm_tool/providers/anthropic_langchain.py
git_llm_tool/providers/azure_openai_langchain.py
git_llm_tool/providers/base.py
git_llm_tool/providers/factory.py
git_llm_tool/providers/gemini_langchain.py
git_llm_tool/providers/langchain_base.py
git_llm_tool/providers/ollama_langchain.py
git_llm_tool/providers/openai_langchain.py
git_llm_tool-0.1.20.dist-info/LICENSE
git_llm_tool-0.1.20.dist-info/METADATA
git_llm_tool-0.1.20.dist-info/WHEEL
git_llm_tool-0.1.20.dist-info/entry_points.txt
git_llm_tool-0.1.20.dist-info/RECORD
