Metadata-Version: 2.3
Name: git-llm-tool
Version: 0.1.20
Summary: AI-powered git commit message and changelog generator
License: MIT
Keywords: git,commit,llm,ai,automation,jira,conventional-commits
Author: skyler-gogolook
Author-email: skyler.lo@gogolook.com
Requires-Python: >=3.10,<4.0
Classifier: Development Status :: 3 - Alpha
Classifier: Intended Audience :: Developers
Classifier: License :: OSI Approved :: MIT License
Classifier: Operating System :: OS Independent
Classifier: Programming Language :: Python :: 3
Classifier: Programming Language :: Python :: 3.10
Classifier: Programming Language :: Python :: 3.11
Classifier: Programming Language :: Python :: 3.12
Classifier: Programming Language :: Python :: 3.13
Classifier: Topic :: Software Development :: Libraries :: Python Modules
Classifier: Topic :: Software Development :: Version Control :: Git
Classifier: Topic :: Utilities
Requires-Dist: anthropic (>=0.30.0,<0.31.0)
Requires-Dist: click (>=8.1.0,<9.0.0)
Requires-Dist: google-generativeai (>=0.5.0,<0.6.0)
Requires-Dist: halo (>=0.0.31,<0.0.32)
Requires-Dist: langchain (>=0.2.0,<0.3.0)
Requires-Dist: langchain-anthropic (>=0.1.23,<0.2.0)
Requires-Dist: langchain-google-genai (>=1.0.0,<2.0.0)
Requires-Dist: langchain-ollama (>=0.1.0,<0.2.0)
Requires-Dist: langchain-openai (>=0.1.0,<0.2.0)
Requires-Dist: openai (>=1.0.0,<2.0.0)
Requires-Dist: pyyaml (>=6.0,<7.0)
Requires-Dist: tiktoken (>=0.7.0,<0.8.0)
Project-URL: Documentation, https://github.com/z0890142/git-llm-tool#readme
Project-URL: Homepage, https://github.com/z0890142/git-llm-tool
Project-URL: Repository, https://github.com/z0890142/git-llm-tool
